{
  "english": {
    "credits": "Credits",
    "exit": "Exit",
    "gameTitleBlockBlitz": "Block Blitz",
    "gameTitleCosmicSentinel": "Cosmic Sentinel",
    "gameTitleGalaxyAssault": "Galaxy Assault",
    "gameTitleLilyLeap": "Lily Leap",
    "gameTitlePaddleDash": "Paddle Dash",
    "gameTitleRocketRun": "Rocket Run",
    "gameTitleStellarStorm": "Stellar Storm",
    "gameTitleWingSoar": "Wing Soar",
    "gameoverEnemyScore": "Enemy Score",
    "gameoverHighScore": "High Score",
    "gameoverHighScores": "High Scores",
    "gameoverPass": "Pass",
    "gameoverTitle": "Game Over",
    "gameoverYouLose": "You Lose",
    "gameoverYouWon": "You Won",
    "gameoverYourScore": "Your Score",
    "menuContinue": "Continue",
    "menuNewGame": "New game",
    "menuPause": "Pause",
    "menuSelectGame": "Select game",
    "menuSoon": "(Soon)",
    "menuStart": "Start",
    "optionDisplay": "Display",
    "optionFullScreen": "Fullscreen",
    "optionLanguage": "Language",
    "optionLanguageEnglish": "English",
    "optionLanguageFrench": "French",
    "optionMusic": "Music",
    "optionNoFullScreen": "Windowed",
    "optionSound": "Sound",
    "optionVolumeHigh": "High",
    "optionVolumeLow": "Low",
    "optionVolumeMedium": "Medium",
    "options": "Options"
  },
  "french": {
    "credits": "Crédits",
    "exit": "Quitter",
    "gameTitleBlockBlitz": "Block Blitz",
    "gameTitleCosmicSentinel": "Cosmic Sentinel",
    "gameTitleGalaxyAssault": "Galaxy Assault",
    "gameTitleLilyLeap": "Lily Leap",
    "gameTitlePaddleDash": "Paddle Dash",
    "gameTitleRocketRun": "Rocket Run",
    "gameTitleStellarStorm": "Stellar Storm",
    "gameTitleWingSoar": "Wing Soar",
    "gameoverEnemyScore": "Score de l'ennemi",
    "gameoverHighScore": "Meilleur Score",
    "gameoverHighScores": "Meilleurs Scores",
    "gameoverPass": "Passes",
    "gameoverTitle": "Partie terminée",
    "gameoverYouLose": "Vous avez perdu",
    "gameoverYouWon": "Vous avez gagné",
    "gameoverYourScore": "Votre score",
    "menuContinue": "Continuer",
    "menuNewGame": "Nouvelle partie",
    "menuPause": "Pause",
    "menuSelectGame": "Sélection du jeu",
    "menuSoon": "(Bientôt)",
    "menuStart": "Démarrer",
    "optionDisplay": "Affichage",
    "optionFullScreen": "Plein Écran",
    "optionLanguage": "Langue",
    "optionLanguageEnglish": "Anglais",
    "optionLanguageFrench": "Français",
    "optionMusic": "Musique",
    "optionNoFullScreen": "Fenêtré",
    "optionSound": "Son",
    "optionVolumeHigh": "Fort",
    "optionVolumeLow": "Faible",
    "optionVolumeMedium": "Moyen",
    "options": "Options"
  }
}
